{"controller":{"interface":{"/pushButton/Sleep":{"interfaceType":"pushButton","eventType":"nState","message":["mousedown"],"position":{"x":"50.53%","y":"25.21%","width":"23.97%","height":"13.87%"},"orientation":"h","numStates":2,"color":"#555555"},"/pushButton/START":{"interfaceType":"pushButton","eventType":"nState","message":["mousedown"],"position":{"x":"2.52%","y":"2.53%","width":"17.20%","height":"11.66%"},"orientation":"h","numStates":2,"color":"green"},"/pushButton/alloff":{"interfaceType":"pushButton","eventType":"nState","message":["mousedown"],"position":{"x":"88.76%","y":"0.68%","width":"8.72%","height":"6.25%"},"orientation":"h","numStates":2,"color":"red"},"/pushButton/knock":{"interfaceType":"pushButton","eventType":"nState","message":["mousedown"],"position":{"x":"4.56%","y":"21.96%","width":"40.27%","height":"15.03%"},"orientation":"h","numStates":2,"color":"brown"},"/hslider/creak":{"interfaceType":"hslider","eventType":"range","message":["mousedown"],"position":{"x":"6.47%","y":"87.50%","width":"74.58%","height":"7.77%"},"orientation":"h","numStates":2,"color":"yellow"},"/vslider/sono":{"interfaceType":"vslider","eventType":"range","message":["mousedown"],"position":{"x":"83.21%","y":"23.99%","width":"13.19%","height":"51.86%"},"orientation":"v","numStates":2,"color":"blue"},"/nStateButton/sonoONOFF":{"interfaceType":"nStateButton","eventType":"nState","message":["mousedown"],"position":{"x":"85.37%","y":"80.07%","width":"13.19%","height":"7.77%"},"orientation":"h","numStates":"2","color":"blue"},"/nStateButton/Thunder":{"interfaceType":"nStateButton","eventType":"nState","message":["mousedown"],"position":{"x":"26.99%","y":"6.08%","width":"64.60%","height":"14.53%"},"orientation":"h","numStates":"4","color":"purple"},"/pushButton/MIC":{"interfaceType":"pushButton","eventType":"nState","message":["mousedown"],"position":{"x":"11.88%","y":"46.19%","width":"50.11%","height":"32.32%"},"orientation":"h","numStates":2,"color":"green"}}},"scenes":[{"name":"Default","sounds":["CreakyDoor|0","RainLoop|1","MonsterMetaMic|2","KnockOnWood|3","ICMCStory/sonobp1|4","jsaMetaDrone2|5","ICMCStory/ThunderSample0|6","ICMCStory/ThunderSample1|7","ICMCStory/ThunderSample2|8"],"handlers":{"/pushButton/Sleep":{"type":"nState","description":"undefined","states":[[[],[],[],[],[],[{"name":"play","type":"range","value":0}],[],[],[]],[[],[],[],[],[],[{"name":"play","type":"range","value":1}],[],[],[]]],"numStates":2},"/pushButton/START":{"type":"nState","description":"undefined","states":[[[],[],[{"name":"play","type":"range","value":1}],[],[],[],[],[],[]],[[{"name":"play","type":"range","value":1}],[{"name":"play","type":"range","value":1}],[],[],[],[],[],[],[]]],"numStates":2},"/pushButton/alloff":{"type":"nState","description":"undefined","states":[[[],[],[],[],[],[],[],[],[]],[[],[{"name":"play","type":"range","value":0}],[],[],[{"name":"play","type":"range","value":0}],[],[],[],[]]],"numStates":2},"/pushButton/knock":{"type":"nState","description":"undefined","states":[[[],[],[],[{"name":"play","type":"range","value":0}],[],[],[],[],[]],[[],[],[],[{"name":"play","type":"range","value":1}],[],[],[],[],[]]],"numStates":2},"/hslider/creak":{"type":"range","description":"undefined","max":[[{"name":"Door Swing Speed","type":"range","value":1}],[],[],[],[],[],[],[],[]],"min":[[{"name":"Door Swing Speed","type":"range","value":0}],[],[],[],[],[],[],[],[]],"numStates":2},"/vslider/sono":{"type":"range","description":"undefined","max":[[],[],[],[],[{"name":"Position","type":"range","value":1}],[],[],[],[]],"min":[[],[],[],[],[{"name":"Position","type":"range","value":0}],[],[],[],[]],"numStates":2},"/nStateButton/sonoONOFF":{"type":"nState","description":"undefined","states":[[[],[],[],[],[{"name":"play","type":"range","value":0}],[],[],[],[]],[[],[],[],[],[{"name":"play","type":"range","value":1}],[],[],[],[]]],"numStates":"2"},"/nStateButton/Thunder":{"type":"nState","description":"undefined","states":[[[],[],[],[],[],[],[{"name":"play","type":"range","value":0}],[{"name":"play","type":"range","value":0}],[{"name":"play","type":"range","value":0}]],[[],[],[],[],[],[],[{"name":"play","type":"range","value":1}],[{"name":"play","type":"range","value":0}],[{"name":"play","type":"range","value":0}]],[[],[],[],[],[],[],[{"name":"play","type":"range","value":0}],[{"name":"play","type":"range","value":1}],[{"name":"play","type":"range","value":0}]],[[],[],[],[],[],[],[{"name":"play","type":"range","value":0}],[{"name":"play","type":"range","value":0}],[{"name":"play","type":"range","value":1}]]],"numStates":"4"},"/pushButton/MIC":{"type":"nState","description":"undefined","states":[[[],[],[{"name":"DryWet","type":"range","value":0}],[],[],[],[],[],[]],[[],[],[{"name":"DryWet","type":"range","value":1}],[],[],[],[],[],[]]],"numStates":2}}}]}